celery_rpc/__init__.py
celery_rpc/app.py
celery_rpc/base.py
celery_rpc/client.py
celery_rpc/codecs.py
celery_rpc/config.py
celery_rpc/exceptions.py
celery_rpc/models.py
celery_rpc/tasks.py
celery_rpc/utils.py
celery_rpc/runtests/__init__.py
celery_rpc/runtests/runtests.py
celery_rpc/runtests/settings.py
celery_rpc/tests/__init__.py
celery_rpc/tests/factories.py
celery_rpc/tests/models.py
celery_rpc/tests/tasks.py
celery_rpc/tests/test_client.py
celery_rpc/tests/test_codecs.py
celery_rpc/tests/test_errors.py
celery_rpc/tests/test_m2m.py
celery_rpc/tests/test_pipeline.py
celery_rpc/tests/test_tasks.py
celery_rpc/tests/tests.py
celery_rpc/tests/utils.py
djangoceleryrpc-4.0.0.dist-info/LICENSE
djangoceleryrpc-4.0.0.dist-info/METADATA
djangoceleryrpc-4.0.0.dist-info/WHEEL
djangoceleryrpc-4.0.0.dist-info/top_level.txt
djangoceleryrpc-4.0.0.dist-info/RECORD
