Metadata-Version: 2.1
Name: djangoceleryrpc
Version: 4.0.0
Summary: Remote access from one system to models and functions of another one using Celery machinery.
Home-page: https://github.com/just-work/django-celery-rpc
Author: axeman
Author-email: alex.manaev@gmail.com
License: Public
Classifier: Development Status :: 6 - Mature
Classifier: Environment :: Console
Classifier: Intended Audience :: Developers
Classifier: Framework :: Django
Classifier: Framework :: Django :: 1.4
Classifier: Framework :: Django :: 1.5
Classifier: Framework :: Django :: 1.6
Classifier: Framework :: Django :: 1.7
Classifier: Framework :: Django :: 1.8
Classifier: Framework :: Django :: 1.9
Classifier: Framework :: Django :: 1.10
Classifier: Framework :: Django :: 1.11
Classifier: Framework :: Django :: 2.0
Classifier: Framework :: Django :: 2.1
Classifier: Framework :: Django :: 2.2
Classifier: Framework :: Django :: 3.0
Classifier: Framework :: Django :: 3.1
Classifier: Framework :: Django :: 3.2
Classifier: Framework :: Django :: 4.0
Classifier: Operating System :: POSIX
Classifier: Programming Language :: Python :: 2.7
Classifier: Programming Language :: Python :: 3.5
Classifier: Programming Language :: Python :: 3.6
Classifier: Programming Language :: Python :: 3.7
Classifier: Programming Language :: Python :: 3.8
Classifier: Programming Language :: Python :: 3.9
Classifier: Programming Language :: Python :: 3.10
License-File: LICENSE
Requires-Dist: celery (<5.3.0,>=3.1.5)
Requires-Dist: jsonpickle (<2.1.0,>=0.8.0)
Requires-Dist: six
Provides-Extra: server
Requires-Dist: django (<4.1,>=1.3) ; extra == 'server'
Requires-Dist: djangorestframework (<3.14,>=2.3) ; extra == 'server'
